{
  "display": true,
  "featured": false,
  "sortNumbers": [{ "since": 2021 }],
  "logo": {
    "icon": "infinitescroll-square.png",
    "full": "infinitescroll-square.png"
  },
  "name": "InfiniteScroll",
  "org": "",
  "description": {
    "short": "Interoperable tools for the Filecoin network.",
    "long": "InfiniteScroll is a subversive software for optimistic internets."
  },
  "primaryCta": { "url": "//infinitescroll.org", "text": "Project Website" },
  "links": [
    {
      "label": "Website",
      "links": [{ "url": "//infinitescroll.org", "text": "infinitescroll.org" }]
    },
    {
      "label": "Repo",
      "links": [
        {
          "url": "//github.com/infinitescroll",
          "text": "github.com/infinitescroll"
        }
      ]
    },
    { "label": "Docs", "links": [{ "url": "", "text": "" }] }
  ],
  "keyInfo": [{ "label": "Using Filecoin since", "value": 2021 }],
  "video": "",
  "stats": [
    { "label": "", "value": "" },
    { "label": "", "value": "" },
    { "label": "", "value": "" }
  ],
  "ctaCard": { "title": "", "description": "", "buttonText": "", "url": "" },
  "taxonomies": [
    { "slug": "project-category", "tags": ["developer-tools"] },
    { "slug": "storage-type", "tags": ["general-storage"] },
    { "slug": "software-type", "tags": ["none"] },
    { "slug": "tooling", "tags": ["ipfs-http-client"] },
    { "slug": "pipeline", "tags": [""] }
  ]
}
